noise_shaper.v
`timescale 1ns/1ps

// ============================================================================
// Module: noise_shaper
// Description:
//   This module implements a noise shaper for the delta-sigma modulator.
//   It combines the three carry outputs from the MASH stages to produce a
//   small signed fractional output.
//
//   Inputs:
//     - clk: clock signal
//     - rst_n: active-low asynchronous reset signal
//     - c1: carry output from the first MASH stage
//     - c2: carry output from the second MASH stage
//     - c3: carry output from the third MASH stage
//     
//   Outputs:
//     - out_f: signed fractional output, width is 4 bits
//
//   Notes:
//     - The noise shaper is a digital filter that shapes the quantization 
//       noise to high frequencies.
//     - Implements: out_f(z) = c1 + (z^-1 - 1)*c2 + (z^-1 - 1)^2*c3
// ============================================================================

module noise_shaper (
    input wire        clk,
    input wire        rst_n,
    input wire        c1,
    input wire        c2,
    input wire        c3,
    output reg signed [3:0] out_f
);

    // DUMMY IMPLEMENTATION - TO BE REPLACED WITH ACTUAL LOGIC
    // For now, just output zero to allow compilation
    always @(posedge clk or negedge rst_n) begin
        if (!rst_n) begin
            out_f <= 4'sd0;
        end else begin
            // Dummy: just output zero
            out_f <= 4'sd0;
        end
    end

endmodule

mash_stage.v
`timescale 1ns/1ps

// ============================================================================
// Module: mash_stage
// Description:
//   This module implements a first-order delta-sigma modulator stage.
//   It accumulates the input value and produces a carry and an error term.
//
//   Parameters:
//     - WIDTH: width of the input and output values (default: 16 bits)
//
//   Inputs:
//     - clk: clock signal
//     - rst_n: active-low asynchronous reset signal
//     - in_val: input value to accumulate [WIDTH-1:0]
//
//   Outputs:
//     - c_out: carry output, width is 1 bit (1-bit Quantizer)
//     - e_out: error output, width is [WIDTH-1:0]
//
//   Notes:
//     - The input value is accumulated on every clock cycle.
//     - The carry output is the overflow/carry bit.
//     - The error output is the remaining sum without the carry.
// ============================================================================

module mash_stage #(
    parameter WIDTH = 16
)(
    input wire                clk,
    input wire                rst_n,
    input wire [WIDTH-1:0]    in_val,
    output reg [WIDTH-1:0]    e_out,
    output reg                c_out
);

    // DUMMY IMPLEMENTATION - TO BE REPLACED WITH ACTUAL LOGIC
    // For now, just pass through zeros to allow compilation
    always @(posedge clk or negedge rst_n) begin
        if (!rst_n) begin
            e_out <= {WIDTH{1'b0}};
            c_out <= 1'b0;
        end else begin
            // Dummy: just output zeros
            e_out <= {WIDTH{1'b0}};
            c_out <= 1'b0;
        end
    end

endmodule

M216A_TopModule.v
`timescale 1ns/1ps

// ============================================================================
// Module: M216A_TopModule
// Description:
//   Top-level MASH 1-1-1 delta-sigma modulator for the ECE M216A project.
//
//   Inputs:
//     - clk   : system clock (500 MHz)
//     - rst_n : active-low async reset
//     - in_i  : 4-bit integer part of divide ratio (3..11)
//     - in_f  : 16-bit fractional part of divide ratio (0..65535)
//
//   Output:
//     - out   : 4-bit divide value = in_i + out_f
//
//   Architecture:
//     - Three cascaded delta-sigma stages (mash_stage):
//         stage1 integrates in_f
//         stage2 integrates e1
//         stage3 integrates e2
//       Each stage outputs a carry bit (c1/c2/c3) and an error term (e1/e2/e3).
//
//     - A noise_shaper block combines c1, c2, c3 to produce a small signed
//       fractional correction out_f in approximately [-3..+4].
//
//     - The final output is:
//         out = in_i + out_f
// ============================================================================

module M216A_TopModule (
    input wire clk,                 // 500 MHz clock
    input wire rst_n,               // active-low reset
    input wire [3:0] in_i,          // integer part, restricted to range of 3..11
    input wire [15:0] in_f,         // fractional part (0..65535)
    output wire [3:0] out           // instantaneous divide value
);

    // Connect Mash stages here...
    // Remember from the project diagram...
    // 3 Integrator stages, each produce a 16b error signal, e1, e2, e3 (tossed)
    // 3 Integrators, each produce a 1b carry signals, c1, c2, c3
    wire [15:0] e1, e2, e3;         // error outputs
    wire        c1, c2, c3;         // carry outputs (1b Quantizer)

    // ========================================================
    // INTEGRATOR STAGES
    // --------------------------------------------------------
    // Build the Integrators together...
    // Input on one end is in_
    // in_f -> stage 1
    // e1 -> stage 2
    // e2 -> stage 3
    // e3 -> discarded
    // 3 Outputs c1, c2, c3 go to the noise shaping later
    // ========================================================

    // Stage 1: integrates the fractional input in_f
    mash_stage #(
        .WIDTH   (16)
    ) stage1 (
        .clk     (clk),
        .rst_n   (rst_n),
        .in_val  (in_f),
        .e_out   (e1),
        .c_out   (c1)
    );

    // Stage 2: integrates e1
    mash_stage #(
        .WIDTH   (16)
    ) stage2 (
        .clk     (clk),
        .rst_n   (rst_n),
        .in_val  (e1),
        .e_out   (e2),
        .c_out   (c2)
    );

    // Stage 3: integrates e2
    mash_stage #(
        .WIDTH   (16)
    ) stage3 (
        .clk     (clk),
        .rst_n   (rst_n),
        .in_val  (e2),
        .e_out   (e3),
        .c_out   (c3)
    );

    // ========================================================
    // NOISE SHAPING
    // --------------------------------------------------------
    // Build the Noise Shaper...
    // c1, c2, c3 -> into the noise shaper
    // out_f -> mixed with in_N to get the OUT signal
    // OUT generated from out_f and in_i
    // ========================================================

    wire signed [3:0] out_f;

    noise_shaper ns (
        .clk    (clk),
        .rst_n  (rst_n),
        .c1     (c1),
        .c2     (c2),
        .c3     (c3),
        .out_f  (out_f)
    );


    // ========================================================
    // FINAL OUTPUT COMBINATION
    // --------------------------------------------------------
    // Build the Final Output Combiner...
    // in_i and out_f -> OUT signal
    // OUT signal is the final output
    // in_i is 4b unsigned
    // out_f is 4b signed
    // OUT is temporarily stored as 5b signed
    // OUT is then truncated to 4b unsigned
    // ========================================================

    reg [3:0] out_reg;

    // 5-bit signed intermediate to handle signed addition
    wire signed [4:0] out_sum_full = $signed({1'b0, in_i}) + $signed(out_f);

    always @(posedge clk or negedge rst_n) begin
        if (!rst_n) begin
            out_reg <= 4'd0;
        end else begin
            // Keep the lower 4 bits as the divide value
            out_reg <= out_sum_full[3:0];
        end
    end

    assign out = out_reg;

endmodule

EE216A_Testbench.v
`timescale 1ns/1ps

// ============================================================================
// Module: EE216A_Testbench
// Description:
//   Testbench for the M216A_TopModule MASH 1-1-1 delta-sigma modulator.
//   
//   Test Strategy:
//     - Edge cases: Test minimum (in_i=3) and maximum (in_i=11) values
//     - Random cases: Test at least 3 random valid input combinations
//     - Verification: Average the output over many cycles and compare to
//       expected value: in_i + in_f/65536
// ============================================================================

module EE216A_Testbench;

    // -------------------------------------------------------------------------
    // DUT I/O signals
    // -------------------------------------------------------------------------
    reg         clk;
    reg         rst_n;
    reg  [3:0]  in_i;
    reg  [15:0] in_f;
    wire [3:0]  out;

    // -------------------------------------------------------------------------
    // Instantiate the DUT
    // -------------------------------------------------------------------------
    M216A_TopModule dut (
        .clk  (clk),
        .rst_n(rst_n),
        .in_i (in_i),
        .in_f (in_f),
        .out  (out)
    );

    // -------------------------------------------------------------------------
    // Clock generation: 500 MHz -> 2 ns period -> toggle every 1 ns
    // -------------------------------------------------------------------------
    initial begin
        clk = 1'b0;
        forever #1 clk = ~clk;
    end

    // -------------------------------------------------------------------------
    // Variables for averaging / checking tests
    // -------------------------------------------------------------------------
    integer cycle_count;
    integer sum_out;
    real    avg_out;
    real    expected_avg;
    real    error;
    real    error_tolerance;
    integer N_CYCLES;
    integer test_count;
    integer pass_count;
    integer fail_count;

    // -------------------------------------------------------------------------
    // VCD dump for waveform viewing and power analysis
    // -------------------------------------------------------------------------
    initial begin
        $dumpfile("M216A_TopModule.vcd");
        $dumpvars(0, EE216A_Testbench);
    end

    // -------------------------------------------------------------------------
    // Task: run_avg_test
    //   - Applies (ti, tf) as (in_i, in_f)
    //   - Waits a few warm-up cycles
    //   - Averages 'out' over 'cycles' cycles
    //   - Computes expected average = ti + tf / 65536.0
    //   - Prints measured vs expected and pass/fail
    // -------------------------------------------------------------------------
    task run_avg_test;
        input  [3:0]  ti;
        input  [15:0] tf;
        input  integer cycles;
        input  [80*8:1] test_name;  // String for test description
        begin
            test_count = test_count + 1;
            
            in_i = ti;
            in_f = tf;

            // Reset sum
            sum_out = 0;

            // Let the modulator settle after changing inputs
            repeat (10) @(posedge clk);

            // Average over 'cycles' clock periods
            for (cycle_count = 0; cycle_count < cycles; cycle_count = cycle_count + 1) begin
                @(posedge clk);
                sum_out = sum_out + out;
            end

            // Compute measured average
            avg_out = sum_out;
            avg_out = avg_out / cycles;

            // Compute expected average: N.f = in_i + in_f/2^16
            expected_avg = ti + (tf / 65536.0);

            // Error
            error = avg_out - expected_avg;

            // Check pass/fail (tolerance for averaging error)
            error_tolerance = 0.01;  // Allow 1% error due to finite averaging

            $display("=====================================================");
            $display("TEST %0d: %0s", test_count, test_name);
            $display("-----------------------------------------------------");
            $display("  Input:  in_i = %0d, in_f = %0d (0x%04h)", ti, tf, tf);
            $display("  Cycles averaged: %0d", cycles);
            $display("  Sum of outputs:  %0d", sum_out);
            $display("  Expected avg:    %0.6f", expected_avg);
            $display("  Measured avg:    %0.6f", avg_out);
            $display("  Error:           %0.6f", error);
            
            if ((error < error_tolerance) && (error > -error_tolerance)) begin
                $display("  Result: PASS");
                pass_count = pass_count + 1;
            end else begin
                $display("  Result: FAIL (error exceeds tolerance)");
                fail_count = fail_count + 1;
            end
            $display("=====================================================\n");
        end
    endtask

    // -------------------------------------------------------------------------
    // Main stimulus and tests
    // -------------------------------------------------------------------------
    initial begin
        // ---------------------------------------------------------------------
        // Initialize
        // ---------------------------------------------------------------------
        rst_n = 1'b0;
        in_i  = 4'd0;
        in_f  = 16'd0;
        test_count = 0;
        pass_count = 0;
        fail_count = 0;

        N_CYCLES = 5000;  // Number of cycles to average for each test

        $display("\n");
        $display("========================================================");
        $display("  M216A DELTA-SIGMA MODULATOR TESTBENCH");
        $display("========================================================");
        $display("  Clock: 500 MHz (2ns period)");
        $display("  Averaging window: %0d cycles", N_CYCLES);
        $display("========================================================\n");

        // Hold reset low for a few ns
        #10;
        rst_n = 1'b1;
        #10;

        // ---------------------------------------------------------------------
        // EDGE CASE TESTS
        // ---------------------------------------------------------------------
        $display("\n>>> EDGE CASE TESTS <<<\n");

        // Test 1: Minimum in_i (3), minimum in_f (0)
        run_avg_test(4'd3, 16'd0, N_CYCLES, "Edge: Min in_i=3, Min in_f=0");

        // Test 2: Minimum in_i (3), maximum in_f (65535)
        run_avg_test(4'd3, 16'hFFFF, N_CYCLES, "Edge: Min in_i=3, Max in_f=65535");

        // Test 3: Maximum in_i (11), minimum in_f (0)
        run_avg_test(4'd11, 16'd0, N_CYCLES, "Edge: Max in_i=11, Min in_f=0");

        // Test 4: Maximum in_i (11), maximum in_f (65535)
        run_avg_test(4'd11, 16'hFFFF, N_CYCLES, "Edge: Max in_i=11, Max in_f=65535");

        // ---------------------------------------------------------------------
        // RANDOM CASE TESTS
        // ---------------------------------------------------------------------
        $display("\n>>> RANDOM CASE TESTS <<<\n");

        // Test 5: Random case 1 - in_i=5, in_f=12345
        run_avg_test(4'd5, 16'd12345, N_CYCLES, "Random: in_i=5, in_f=12345");

        // Test 6: Random case 2 - in_i=7, in_f=32768 (0.5)
        run_avg_test(4'd7, 16'd32768, N_CYCLES, "Random: in_i=7, in_f=32768 (0.5)");

        // Test 7: Random case 3 - in_i=8, in_f=32000
        run_avg_test(4'd8, 16'd32000, N_CYCLES, "Random: in_i=8, in_f=32000");

        // Test 8: Random case 4 - in_i=4, in_f=1000
        run_avg_test(4'd4, 16'd1000, N_CYCLES, "Random: in_i=4, in_f=1000");

        // Test 9: Random case 5 - in_i=9, in_f=50000
        run_avg_test(4'd9, 16'd50000, N_CYCLES, "Random: in_i=9, in_f=50000");

        // ---------------------------------------------------------------------
        // Summary
        // ---------------------------------------------------------------------
        $display("\n");
        $display("========================================================");
        $display("  TEST SUMMARY");
        $display("========================================================");
        $display("  Total tests: %0d", test_count);
        $display("  Passed:      %0d", pass_count);
        $display("  Failed:      %0d", fail_count);
        $display("========================================================");
        
        if (fail_count == 0) begin
            $display("  ALL TESTS PASSED!");
        end else begin
            $display("  SOME TESTS FAILED - Review results above");
        end
        $display("========================================================\n");

        // ---------------------------------------------------------------------
        // Done
        // ---------------------------------------------------------------------
        #100;
        $finish;
    end

endmodule

M216A_TopModule.vcd
$date
	Tue Nov 25 21:00:08 2025
$end
$version
	ModelSim Version 2024.2
$end
$timescale
	1ps
$end

$scope module EE216A_Testbench $end
$var reg 1 ! clk $end
$var reg 1 " rst_n $end
$var reg 4 # in_i [3:0] $end
$var reg 16 $ in_f [15:0] $end
$var wire 1 % out [3] $end
$var wire 1 & out [2] $end
$var wire 1 ' out [1] $end
$var wire 1 ( out [0] $end
$var integer 32 ) cycle_count $end
$var integer 32 * sum_out $end
$var real 64 + avg_out $end
$var real 64 , expected_avg $end
$var real 64 - error $end
$var real 64 . error_tolerance $end
$var integer 32 / N_CYCLES $end
$var integer 32 0 test_count $end
$var integer 32 1 pass_count $end
$var integer 32 2 fail_count $end

$scope task run_avg_test $end
$var reg 4 3 ti [3:0] $end
$var reg 16 4 tf [15:0] $end
$var integer 32 5 cycles $end
$var reg 640 6 test_name [640:1] $end
$upscope $end

$scope module dut $end
$var wire 1 7 clk $end
$var wire 1 8 rst_n $end
$var wire 1 9 in_i [3] $end
$var wire 1 : in_i [2] $end
$var wire 1 ; in_i [1] $end
$var wire 1 < in_i [0] $end
$var wire 1 = in_f [15] $end
$var wire 1 > in_f [14] $end
$var wire 1 ? in_f [13] $end
$var wire 1 @ in_f [12] $end
$var wire 1 A in_f [11] $end
$var wire 1 B in_f [10] $end
$var wire 1 C in_f [9] $end
$var wire 1 D in_f [8] $end
$var wire 1 E in_f [7] $end
$var wire 1 F in_f [6] $end
$var wire 1 G in_f [5] $end
$var wire 1 H in_f [4] $end
$var wire 1 I in_f [3] $end
$var wire 1 J in_f [2] $end
$var wire 1 K in_f [1] $end
$var wire 1 L in_f [0] $end
$var wire 1 % out [3] $end
$var wire 1 & out [2] $end
$var wire 1 ' out [1] $end
$var wire 1 ( out [0] $end
$var wire 1 M e1 [15] $end
$var wire 1 N e1 [14] $end
$var wire 1 O e1 [13] $end
$var wire 1 P e1 [12] $end
$var wire 1 Q e1 [11] $end
$var wire 1 R e1 [10] $end
$var wire 1 S e1 [9] $end
$var wire 1 T e1 [8] $end
$var wire 1 U e1 [7] $end
$var wire 1 V e1 [6] $end
$var wire 1 W e1 [5] $end
$var wire 1 X e1 [4] $end
$var wire 1 Y e1 [3] $end
$var wire 1 Z e1 [2] $end
$var wire 1 [ e1 [1] $end
$var wire 1 \ e1 [0] $end
$var wire 1 ] e2 [15] $end
$var wire 1 ^ e2 [14] $end
$var wire 1 _ e2 [13] $end
$var wire 1 ` e2 [12] $end
$var wire 1 a e2 [11] $end
$var wire 1 b e2 [10] $end
$var wire 1 c e2 [9] $end
$var wire 1 d e2 [8] $end
$var wire 1 e e2 [7] $end
$var wire 1 f e2 [6] $end
$var wire 1 g e2 [5] $end
$var wire 1 h e2 [4] $end
$var wire 1 i e2 [3] $end
$var wire 1 j e2 [2] $end
$var wire 1 k e2 [1] $end
$var wire 1 l e2 [0] $end
$var wire 1 m e3 [15] $end
$var wire 1 n e3 [14] $end
$var wire 1 o e3 [13] $end
$var wire 1 p e3 [12] $end
$var wire 1 q e3 [11] $end
$var wire 1 r e3 [10] $end
$var wire 1 s e3 [9] $end
$var wire 1 t e3 [8] $end
$var wire 1 u e3 [7] $end
$var wire 1 v e3 [6] $end
$var wire 1 w e3 [5] $end
$var wire 1 x e3 [4] $end
$var wire 1 y e3 [3] $end
$var wire 1 z e3 [2] $end
$var wire 1 { e3 [1] $end
$var wire 1 | e3 [0] $end
$var wire 1 } c1 $end
$var wire 1 ~ c2 $end
$var wire 1 !! c3 $end
$var wire 1 "! out_f [3] $end
$var wire 1 #! out_f [2] $end
$var wire 1 $! out_f [1] $end
$var wire 1 %! out_f [0] $end
$var reg 4 &! out_reg [3:0] $end
$var wire 1 '! out_sum_full [4] $end
$var wire 1 (! out_sum_full [3] $end
$var wire 1 )! out_sum_full [2] $end
$var wire 1 *! out_sum_full [1] $end
$var wire 1 +! out_sum_full [0] $end

$scope module stage1 $end
$var parameter 32 ,! WIDTH $end
$var wire 1 7 clk $end
$var wire 1 8 rst_n $end
$var wire 1 = in_val [15] $end
$var wire 1 > in_val [14] $end
$var wire 1 ? in_val [13] $end
$var wire 1 @ in_val [12] $end
$var wire 1 A in_val [11] $end
$var wire 1 B in_val [10] $end
$var wire 1 C in_val [9] $end
$var wire 1 D in_val [8] $end
$var wire 1 E in_val [7] $end
$var wire 1 F in_val [6] $end
$var wire 1 G in_val [5] $end
$var wire 1 H in_val [4] $end
$var wire 1 I in_val [3] $end
$var wire 1 J in_val [2] $end
$var wire 1 K in_val [1] $end
$var wire 1 L in_val [0] $end
$var reg 16 -! e_out [15:0] $end
$var reg 1 .! c_out $end
$upscope $end

$scope module stage2 $end
$var parameter 32 /! WIDTH $end
$var wire 1 7 clk $end
$var wire 1 8 rst_n $end
$var wire 1 M in_val [15] $end
$var wire 1 N in_val [14] $end
$var wire 1 O in_val [13] $end
$var wire 1 P in_val [12] $end
$var wire 1 Q in_val [11] $end
$var wire 1 R in_val [10] $end
$var wire 1 S in_val [9] $end
$var wire 1 T in_val [8] $end
$var wire 1 U in_val [7] $end
$var wire 1 V in_val [6] $end
$var wire 1 W in_val [5] $end
$var wire 1 X in_val [4] $end
$var wire 1 Y in_val [3] $end
$var wire 1 Z in_val [2] $end
$var wire 1 [ in_val [1] $end
$var wire 1 \ in_val [0] $end
$var reg 16 0! e_out [15:0] $end
$var reg 1 1! c_out $end
$upscope $end

$scope module stage3 $end
$var parameter 32 2! WIDTH $end
$var wire 1 7 clk $end
$var wire 1 8 rst_n $end
$var wire 1 ] in_val [15] $end
$var wire 1 ^ in_val [14] $end
$var wire 1 _ in_val [13] $end
$var wire 1 ` in_val [12] $end
$var wire 1 a in_val [11] $end
$var wire 1 b in_val [10] $end
$var wire 1 c in_val [9] $end
$var wire 1 d in_val [8] $end
$var wire 1 e in_val [7] $end
$var wire 1 f in_val [6] $end
$var wire 1 g in_val [5] $end
$var wire 1 h in_val [4] $end
$var wire 1 i in_val [3] $end
$var wire 1 j in_val [2] $end
$var wire 1 k in_val [1] $end
$var wire 1 l in_val [0] $end
$var reg 16 3! e_out [15:0] $end
$var reg 1 4! c_out $end
$upscope $end

$scope module ns $end
$var wire 1 7 clk $end
$var wire 1 8 rst_n $end
$var wire 1 } c1 $end
$var wire 1 ~ c2 $end
$var wire 1 !! c3 $end
$var reg 4 5! out_f [3:0] $end
$upscope $end
$upscope $end
$upscope $end
$enddefinitions $end
#0
$dumpvars
0!
0"
b0 #
b0 $
b0 -!
0.!
b0 0!
01!
b0 3!
04!
b0 5!
b0 &!
bx 3
bx 4
bx 6
b10000 ,!
b10000 /!
b10000 2!
bx )
bx *
b1001110001000 /
b0 0
b0 1
b0 2
bx 5
r0 +
r0 ,
r0 -
r0 .
0(
0'
0&
0%
0\
0[
0Z
0Y
0X
0W
0V
0U
0T
0S
0R
0Q
0P
0O
0N
0M
0l
0k
0j
0i
0h
0g
0f
0e
0d
0c
0b
0a
0`
0_
0^
0]
0|
0{
0z
0y
0x
0w
0v
0u
0t
0s
0r
0q
0p
0o
0n
0m
0}
0~
0!!
0%!
0$!
0#!
0"!
0+!
0*!
0)!
0(!
0'!
0L
0K
0J
0I
0H
0G
0F
0E
0D
0C
0B
0A
0@
0?
0>
0=
0<
0;
0:
09
08
07
$end
#1000
1!
17
#2000
0!
07
#3000
1!
17
#4000
0!
07
#5000
1!
17
#6000
0!
07
#7000
1!
17
#8000
0!
07
#9000
1!
17
#10000
1"
0!
18
07
#11000
1!
17
#12000
0!
07
#13000
1!
17
#14000
0!
07
#15000
1!
17
#16000
0!
07
#17000
1!
17
#18000
0!
07
#19000
1!
17
#20000
b11 3
b0 4
b1001110001000 5
b1000101011001000110011101100101001110100010000001001101011010010110111000100000011010010110111001011111011010010011110100110011001011000010000001001101011010010110111000100000011010010110111001011111011001100011110100110000 6
b1 0
b11 #
b0 *
0!
1<
1;
1+!
1*!
07
#21000
1!
17
b11 &!
1(
1'
#22000
0!
07
#23000
1!
17
#24000
0!
07
#25000
1!
17
#26000
0!
07
#27000
1!
17
#28000
0!
07
#29000
1!
17
#30000
0!
07
#31000
1!
17
#32000
0!
07
#33000
1!
17
#34000
0!
07
#35000
1!
17
#36000
0!
07
#37000
1!
17
#38000
0!
07
#39000
1!
17
b0 )
#40000
0!
07
#41000
1!
17
b11 *
b1 )
#42000
0!
07
#43000
1!
17
b110 *
b10 )
#44000
0!
07
#45000
1!
17
b1001 *
b11 )
#46000
0!
07
#47000
1!
17
b1100 *
b100 )
#48000
0!
07
#49000
1!
17
b1111 *
b101 )
#50000
0!
07
#51000
1!
17
b10010 *
b110 )
#52000
0!
07
#53000
1!
17
b10101 *
b111 )
#54000
0!
07
#55000
1!
17
b11000 *
b1000 )
#56000
0!
07
#57000
1!
17
b11011 *
b1001 )
#58000
0!
07
#59000
1!
17
b11110 *
b1010 )
#60000
0!
07
#61000
1!
17
b100001 *
b1011 )
#62000
0!
07
#63000
1!
17
b100100 *
b1100 )
#64000
0!
07
#65000
1!
17
b100111 *
b1101 )
#66000
0!
07
#67000
1!
17
b101010 *
b1110 )
#68000
0!
07
#69000
1!
17
b101101 *
b1111 )
#70000
0!
07
#71000
1!
17
b110000 *
b10000 )
#72000
0!
07
#73000
1!
17
b110011 *
b10001 )
#74000
0!
07
#75000
1!
17
b110110 *
b10010 )
#76000
0!
07
#77000
1!
17
b111001 *
b10011 )
#78000
0!
07
#79000
1!
17
b111100 *
b10100 )
#80000
0!
07
#81000
1!
17
b111111 *
b10101 )
#82000
0!
07
#83000
1!
17
b1000010 *
b10110 )
#84000
0!
07
#85000
1!
17
b1000101 *
b10111 )
#86000
0!
07
#87000
1!
17
b1001000 *
b11000 )
#88000
0!
07
#89000
1!
17
b1001011 *
b11001 )
#90000
0!
07
#91000
1!
17
b1001110 *
b11010 )
#92000
0!
07
#93000
1!
17
b1010001 *
b11011 )
#94000
0!
07
#95000
1!
17
b1010100 *
b11100 )
#96000
0!
07
#97000
1!
17
b1010111 *
b11101 )
#98000
0!
07
#99000
1!
17
b1011010 *
b11110 )
#100000
0!
07
#101000
1!
17
b1011101 *
b11111 )
#102000
0!
07
#103000
1!
17
b1100000 *
b100000 )
#104000
0!
07
#105000
1!
17
b1100011 *
b100001 )
#106000
0!
07
#107000
1!
17
b1100110 *
b100010 )
#108000
0!
07
#109000
1!
17
b1101001 *
b100011 )
#110000
0!
07
#111000
1!
17
b1101100 *
b100100 )
#112000
0!
07
#113000
1!
17
b1101111 *
b100101 )
#114000
0!
07
#115000
1!
17
b1110010 *
b100110 )
#116000
0!
07
#117000
1!
17
b1110101 *
b100111 )
#118000
0!
07
#119000
1!
17
b1111000 *
b101000 )
#120000
0!
07
#121000
1!
17
b1111011 *
b101001 )
#122000
0!
07
#123000
1!
17
b1111110 *
b101010 )
#124000
0!
07
#125000
1!
17
b10000001 *
b101011 )
#126000
0!
07
#127000
1!
17
b10000100 *
b101100 )
#128000
0!
07
#129000
1!
17
b10000111 *
b101101 )
#130000
0!
07
#131000
1!
17
b10001010 *
b101110 )
#132000
0!
07
#133000
1!
17
b10001101 *
b101111 )
#134000
0!
07
#135000
1!
17
b10010000 *
b110000 )
#136000
0!
07
#137000
1!
17
b10010011 *
b110001 )
#138000
0!
07
#139000
1!
17
b10010110 *
b110010 )
#140000
0!
07
#141000
1!
17
b10011001 *
b110011 )
#142000
0!
07
#143000
1!
17
b10011100 *
b110100 )
#144000
0!
07
#145000
1!
17
b10011111 *
b110101 )
#146000
0!
07
#147000
1!
17
b10100010 *
b110110 )
#148000
0!
07
#149000
1!
17
b10100101 *
b110111 )
#150000
0!
07
#151000
1!
17
b10101000 *
b111000 )
#152000
0!
07
#153000
1!
17
b10101011 *
b111001 )
#154000
0!
07
#155000
1!
17
b10101110 *
b111010 )
#156000
0!
07
#157000
1!
17
b10110001 *
b111011 )
#158000
0!
07
#159000
1!
17
b10110100 *
b111100 )
#160000
0!
07
#161000
1!
17
b10110111 *
b111101 )
#162000
0!
07
#163000
1!
17
b10111010 *
b111110 )
#164000
0!
07
#165000
1!
17
b10111101 *
b111111 )
#166000
0!
07
#167000
1!
17
b11000000 *
b1000000 )
#168000
0!
07
#169000
1!
17
b11000011 *
b1000001 )
#170000
0!
07
#171000
1!
17
b11000110 *
b1000010 )
#172000
0!
07
#173000
1!
17
b11001001 *
b1000011 )
#174000
0!
07
#175000
1!
17
b11001100 *
b1000100 )
#176000
0!
07
#177000
1!
17
b11001111 *
b1000101 )
#178000
0!
07
#179000
1!
17
b11010010 *
b1000110 )
#180000
0!
07
#181000
1!
17
b11010101 *
b1000111 )
#182000
0!
07
#183000
1!
17
b11011000 *
b1001000 )
#184000
0!
07
#185000
1!
17
b11011011 *
b1001001 )
#186000
0!
07
#187000
1!
17
b11011110 *
b1001010 )
#188000
0!
07
#189000
1!
17
b11100001 *
b1001011 )
#190000
0!
07
#191000
1!
17
b11100100 *
b1001100 )
#192000
0!
07
#193000
1!
17
b11100111 *
b1001101 )
#194000
0!
07
#195000
1!
17
b11101010 *
b1001110 )
#196000
0!
07
#197000
1!
17
b11101101 *
b1001111 )
#198000
0!
07
#199000
1!
17
b11110000 *
b1010000 )
#200000
0!
07
#201000
1!
17
b11110011 *
b1010001 )
#202000
0!
07
#203000
1!
17
b11110110 *
b1010010 )
#204000
0!
07
#205000
1!
17
b11111001 *
b1010011 )
#206000
0!
07
#207000
1!
17
b11111100 *
b1010100 )
#208000
0!
07
#209000
1!
17
b11111111 *
b1010101 )
#210000
0!
07
#211000
1!
17
b100000010 *
b1010110 )
#212000
0!
07
#213000
1!
17
b100000101 *
b1010111 )
#214000
0!
07
#215000
1!
17
b100001000 *
b1011000 )
#216000
0!
07
#217000
1!
17
b100001011 *
b1011001 )
#218000
0!
07
#219000
1!
17
b100001110 *
b1011010 )
#220000
0!
07
#221000
1!
17
b100010001 *
b1011011 )
#222000
0!
07
#223000
1!
17
b100010100 *
b1011100 )
#224000
0!
07
#225000
1!
17
b100010111 *
b1011101 )
#226000
0!
07
#227000
1!
17
b100011010 *
b1011110 )
#228000
0!
07
#229000
1!
17
b100011101 *
b1011111 )
#230000
0!
07
#231000
1!
17
b100100000 *
b1100000 )
#232000
0!
07
#233000
1!
17
b100100011 *
b1100001 )
#234000
0!
07
#235000
1!
17
b100100110 *
b1100010 )
#236000
0!
07
#237000
1!
17
b100101001 *
b1100011 )
#238000
0!
07
#239000
1!
17
b100101100 *
b1100100 )
#240000
0!
07
#241000
1!
17
b100101111 *
b1100101 )
#242000
0!
07
#243000
1!
17
b100110010 *
b1100110 )
#244000
0!
07
#245000
1!
17
b100110101 *
b1100111 )
#246000
0!
07
#247000
1!
17
b100111000 *
b1101000 )
#248000
0!
07
#249000
1!
17
b100111011 *
b1101001 )
#250000
0!
07
#251000
1!
17
b100111110 *
b1101010 )
#252000
0!
07
#253000
1!
17
b101000001 *
b1101011 )
#254000
0!
07
#255000
1!
17
b101000100 *
b1101100 )
#256000
0!
07
#257000
1!
17
b101000111 *
b1101101 )
#258000
0!
07
#259000
1!
17
b101001010 *
b1101110 )
#260000
0!
07
#261000
1!
17
b101001101 *
b1101111 )
#262000
0!
07
#263000
1!
17
b101010000 *
b1110000 )
#264000
0!
07
#265000
1!
17
b101010011 *
b1110001 )
#266000
0!
07
#267000
1!
17
b101010110 *
b1110010 )
#268000
0!
07
#269000
1!
17
b101011001 *
b1110011 )
#270000
0!
07
#271000
1!
17
b101011100 *
b1110100 )
#272000
0!
07
#273000
1!
17
b101011111 *
b1110101 )
#274000
0!
07
#275000
1!
17
b101100010 *
b1110110 )
#276000
0!
07
#277000
1!
17
b101100101 *
b1110111 )
#278000
0!
07
#279000
1!
17
b101101000 *
b1111000 )
#280000
0!
07
#281000
1!
17
b101101011 *
b1111001 )
#282000
0!
07
#283000
1!
17
b101101110 *
b1111010 )
#284000
0!
07
#285000
1!
17
b101110001 *
b1111011 )
#286000
0!
07
#287000
1!
17
b101110100 *
b1111100 )
#288000
0!
07
#289000
1!
17
b101110111 *
b1111101 )
#290000
0!
07
#291000
1!
17
b101111010 *
b1111110 )
#292000
0!
07
#293000
1!
17
b101111101 *
b1111111 )
#294000
0!
07
#295000
1!
17
b110000000 *
b10000000 )
#296000
0!
07
#297000
1!
17
b110000011 *
b10000001 )
#298000
0!
07
#299000
1!
17
b110000110 *
b10000010 )
#300000
0!
07
#301000
1!
17
b110001001 *
b10000011 )
#302000
0!
07
#303000
1!
17
b110001100 *
b10000100 )
#304000
0!
07
#305000
1!
17
b110001111 *
b10000101 )
#306000
0!
07
#307000
1!
17
b110010010 *
b10000110 )
#308000
0!
07
#309000
1!
17
b110010101 *
b10000111 )
#310000
0!
07
#311000
1!
17
b110011000 *
b10001000 )
#312000
0!
07
#313000
1!
17
b110011011 *
b10001001 )
#314000
0!
07
#315000
1!
17
b110011110 *
b10001010 )
#316000
0!
07
#317000
1!
17
b110100001 *
b10001011 )
#318000
0!
07
#319000
1!
17
b110100100 *
b10001100 )
#320000
0!
07
#321000
1!
17
b110100111 *
b10001101 )
#322000
0!
07
#323000
1!
17
b110101010 *
b10001110 )
#324000
0!
07
#325000
1!
17
b110101101 *
b10001111 )
#326000
0!
07
#327000
1!
17
b110110000 *
b10010000 )
#328000
0!
07
#329000
1!
17
b110110011 *
b10010001 )
#330000
0!
07
#331000
1!
17
b110110110 *
b10010010 )
#332000
0!
07
#333000
1!
17
b110111001 *
b10010011 )
#334000
0!
07
#335000
1!
17
b110111100 *
b10010100 )
#336000
0!
07
#337000
1!
17
b110111111 *
b10010101 )
#338000
0!
07
#339000
1!
17
b111000010 *
b10010110 )
#340000
0!
07
#341000
1!
17
b111000101 *
b10010111 )
#342000
0!
07
#343000
1!
17
b111001000 *
b10011000 )
#344000
0!
07
#345000
1!
17
b111001011 *
b10011001 )
#346000
0!
07
